copyforward-0.2.1.dist-info/METADATA
copyforward-0.2.1.dist-info/WHEEL
copyforward-0.2.1.dist-info/licenses/LICENSE
copyforward/__init__.py
copyforward/copyforward.cp312-win_amd64.pyd
copyforward-0.2.1.dist-info/RECORD
