Metadata-Version: 2.4
Name: copyforward
Version: 0.2.1
Classifier: Programming Language :: Rust
Classifier: Programming Language :: Python :: Implementation :: CPython
Classifier: Programming Language :: Python :: 3.10
Classifier: Programming Language :: Python :: 3.11
Classifier: Programming Language :: Python :: 3.12
Requires-Dist: numpy>=1.20
License-File: LICENSE
Summary: Fast similarity search using forward-looking LSH
Author: Sean Gallagher
Requires-Python: >=3.10
Project-URL: Homepage, https://github.com/SeanTater/copyforward
Project-URL: Repository, https://github.com/SeanTater/copyforward
